app/__init__.py
app/search_sites.py
app/settings.py
app/urls.py
app/wsgi.py
app/scripts/__init__.py
app/scripts/manage.py
djangopypi/__init__.py
djangopypi/__version__.py
djangopypi/admin.py
djangopypi/decorators.py
djangopypi/feeds.py
djangopypi/forms.py
djangopypi/http.py
djangopypi/models.py
djangopypi/search_indexes.py
djangopypi/settings.py
djangopypi/signals.py
djangopypi/urls.py
djangopypi/utils.py
djangopypi/management/__init__.py
djangopypi/management/commands/__init__.py
djangopypi/management/commands/loadclassifiers.py
djangopypi/management/commands/ppadd.py
djangopypi/migrations/0001_initial.py
djangopypi/migrations/0002_refactoring.py
djangopypi/migrations/0003_add_masterindex_mirrorlog.py
djangopypi/migrations/0004_allow_anonymous_distributions.py
djangopypi/migrations/0005_allow_null_distribution_uploader.py
djangopypi/migrations/0006_auto__add_field_package_normalized_name.py
djangopypi/migrations/0007_init_normalized_name.py
djangopypi/migrations/__init__.py
djangopypi/templatetags/__init__.py
djangopypi/templatetags/safemarkup.py
djangopypi/tests/__init__.py
djangopypi/tests/pip.py
djangopypi/views/__init__.py
djangopypi/views/distutils.py
djangopypi/views/packages.py
djangopypi/views/releases.py
djangopypi/views/xmlrpc.py
infi.djangopypi-0.5.dist-info/LICENSE
infi.djangopypi-0.5.dist-info/METADATA
infi.djangopypi-0.5.dist-info/WHEEL
infi.djangopypi-0.5.dist-info/entry_points.txt
infi.djangopypi-0.5.dist-info/namespace_packages.txt
infi.djangopypi-0.5.dist-info/top_level.txt
infi.djangopypi-0.5.dist-info/RECORD
