Metadata-Version: 2.1
Name: infi.djangopypi
Version: 0.5
Summary: Simple PyPI server written in django
Home-page: https://github.com/Infinidat/djangopypi
Author: Arnon Yaari
Author-email: arnony@infinidat.com
License: BSD
Platform: UNKNOWN
Classifier: Intended Audience :: Developers
Classifier: Intended Audience :: System Administrators
Classifier: License :: OSI Approved :: BSD License
Classifier: Operating System :: OS Independent
Classifier: Programming Language :: Python
Classifier: Topic :: Software Development :: Libraries :: Python Modules
Requires-Dist: django-haystack (==2.4.0)
Requires-Dist: django-registration (==1.0)
Requires-Dist: django (<1.7)
Requires-Dist: docutils
Requires-Dist: setuptools
Requires-Dist: south
Requires-Dist: Whoosh
